README.rst
setup.py
warp_prism/__init__.py
warp_prism/_warp_prism.c
warp_prism.egg-info/PKG-INFO
warp_prism.egg-info/SOURCES.txt
warp_prism.egg-info/dependency_links.txt
warp_prism.egg-info/requires.txt
warp_prism.egg-info/top_level.txt