Metadata-Version: 1.1
Name: warp-prism
Version: 0.1.1
Summary: Quickly move data from postgres to numpy or pandas.
Home-page: https://github.com/quantopian/warp_prism
Author: Quantopian Inc.
Author-email: opensource@gmail.com
License: Apache 2.0
Platform: UNKNOWN
Classifier: Development Status :: 5 - Production/Stable
Classifier: Intended Audience :: Developers
Classifier: Intended Audience :: Science/Research
Classifier: License :: OSI Approved :: Apache Software License
Classifier: Natural Language :: English
Classifier: Programming Language :: C
Classifier: Programming Language :: Python :: 3
Classifier: Programming Language :: Python :: Implementation :: CPython
Classifier: Topic :: Scientific/Engineering
